languages/__init__.py
languages/english.py
languages/hindi.py
languages/marathi.py
word2num_converter-1.0.0.dist-info/licenses/LICENSE
word2num_converter-1.0.0.dist-info/METADATA
word2num_converter-1.0.0.dist-info/WHEEL
word2num_converter-1.0.0.dist-info/top_level.txt
word2num_converter-1.0.0.dist-info/RECORD
