Metadata-Version: 2.4
Name: word2num_converter
Version: 1.0.0
Summary: Convert words to numbers in English, Hindi, and Marathi
Home-page: https://github.com/singhchandann/word2num_converter
Author: Chandan Singh
Author-email: chandan21082000@gmail.com
Classifier: Programming Language :: Python :: 3
Classifier: Operating System :: OS Independent
Classifier: Intended Audience :: Developers
Classifier: Natural Language :: Hindi
Classifier: Natural Language :: Marathi
Classifier: Natural Language :: English
Requires-Python: >=3.6
License-File: LICENSE
Dynamic: author
Dynamic: author-email
Dynamic: classifier
Dynamic: description
Dynamic: description-content-type
Dynamic: home-page
Dynamic: license-file
Dynamic: requires-python
Dynamic: summary
